coffee_price/__init__.py
coffee_price/admin.py
coffee_price/apps.py
coffee_price/models.py
coffee_price/tests.py
coffee_price/urls.py
coffee_price/views.py
coffee_price/lib/__init__.py
coffee_price/lib/managers/__init__.py
coffee_price/lib/managers/price.py
coffee_price/lib/serializers/__init__.py
coffee_price/lib/serializers/price.py
coffee_price/lib/services/__init__.py
coffee_price/lib/services/coffee_price.py
coffee_price/migrations/0001_initial.py
coffee_price/migrations/__init__.py
coffee_price/tasks/__init__.py
coffee_price/tasks/get_prices.py
cfhl_coffee_price-1.0.0.dist-info/LICENSE
cfhl_coffee_price-1.0.0.dist-info/METADATA
cfhl_coffee_price-1.0.0.dist-info/WHEEL
cfhl_coffee_price-1.0.0.dist-info/top_level.txt
cfhl_coffee_price-1.0.0.dist-info/RECORD
